SKPANG_LIN_Hat/__init__.py
SKPANG_LIN_Hat/pican_lin.py
SKPANG_LIN_Hat-0.0.1.dist-info/LICENSE.txt
SKPANG_LIN_Hat-0.0.1.dist-info/METADATA
SKPANG_LIN_Hat-0.0.1.dist-info/WHEEL
SKPANG_LIN_Hat-0.0.1.dist-info/top_level.txt
SKPANG_LIN_Hat-0.0.1.dist-info/RECORD
