Metadata-Version: 2.1
Name: SKPANG-LIN-Hat
Version: 0.0.1
Summary: LIN Communications Package
Author: Joseph Szlavik
Author-email: joseph.szlavik@mclaren.com
License-File: LICENSE.txt
